summed/__init__.py
summed/analyzer.py
summed/cli.py
summed/data.py
summed/detector.py
summed/extractor.py
summed/pipeline.py
summed/space.py
summed/summed_api.py
summed/summed_platform.py
summed/translation.py
summed/user.py
summed/utils.py
summed/analysis/__init__.py
summed/analysis/configurations.py
summed/analysis/glossary_lookup.py
summed/analysis/gpt3_summarizer.py
summed/analysis/health_entities.py
summed/analysis/preprocess_text.py
summed/analysis/summarizer.py
summed/analysis/translation.py
summed/analysis/trust_score.py
summed/analysis/trusted_search.py
summed/extraction/__init__.py
summed/extraction/audio_transcribe.py
summed/extraction/docx_extract.py
summed/extraction/form_recognizer.py
summed/extraction/html_extract.py
summed/extraction/image_ocr.py
summed/extraction/plain_text.py
summed-0.1.0.dist-info/AUTHORS.rst
summed-0.1.0.dist-info/LICENSE
summed-0.1.0.dist-info/METADATA
summed-0.1.0.dist-info/WHEEL
summed-0.1.0.dist-info/entry_points.txt
summed-0.1.0.dist-info/top_level.txt
summed-0.1.0.dist-info/RECORD
