Metadata-Version: 2.1
Name: summed
Version: 0.1.0
Summary: SumMed empowers patients and caregivers to better understand medical information
Home-page: https://github.com/whatchacallit/summed
Author: SumMed Team
Author-email: hello@summed.org
License: MIT license
Keywords: summed
Classifier: Development Status :: 2 - Pre-Alpha
Classifier: Intended Audience :: Developers
Classifier: License :: OSI Approved :: MIT License
Classifier: Natural Language :: English
Classifier: Programming Language :: Python :: 3.8
Requires-Python: >=3.8, <3.9
License-File: LICENSE
License-File: AUTHORS.rst
Requires-Dist: Click (>=8.0.3)
Requires-Dist: pydantic (<1.9.0)
Requires-Dist: requests (>=2.26.0)
Requires-Dist: requests-file (>=1.5.1)
Requires-Dist: python-dotenv (>=0.19.2)
Requires-Dist: azure-core (>=1.21.1)
Requires-Dist: azure-storage-blob (>=12.9.0)
Requires-Dist: azure-ai-textanalytics (>=5.1.0)
Requires-Dist: azure-ai-formrecognizer (>=3.1.2)
Requires-Dist: bs4 (>=0.0.1)
Requires-Dist: spacy[lookups] (>=3.2.1)
Requires-Dist: pytextrank (>=3.2.2)
Requires-Dist: en-core-web-sm
Requires-Dist: ru-core-news-sm
Requires-Dist: pt-core-news-sm
Requires-Dist: de-core-news-sm
Requires-Dist: xx-sent-ud-sm
Requires-Dist: openai (>=0.16.0)
Requires-Dist: boilerpy3 (>=1.0.6)
Requires-Dist: pluggy (>=0.13.1)
Requires-Dist: charset-normalizer (>=2.0.12)
Requires-Dist: lxml (>=4.5.0)
Requires-Dist: scispacy (>=0.5.0)
Requires-Dist: pikepdf (>=5.1.3)
Requires-Dist: streamlit (>=1.10.0)
Requires-Dist: fastapi (>=0.85.1)
Requires-Dist: uvicorn (>=0.19.0)
